humblebundle/__init__.py
humblebundle/__main__.py
humblebundle/api.py
humblebundle/get.py
humblebundle.py-0.1.0.dist-info/LICENSE.txt
humblebundle.py-0.1.0.dist-info/METADATA
humblebundle.py-0.1.0.dist-info/WHEEL
humblebundle.py-0.1.0.dist-info/top_level.txt
humblebundle.py-0.1.0.dist-info/RECORD
